stylometry_utils/__init__.py
stylometry_utils/class_Experiment.py
stylometry_utils/experiment_classes.py
stylometry_utils-0.1.3.dist-info/METADATA
stylometry_utils-0.1.3.dist-info/WHEEL
stylometry_utils-0.1.3.dist-info/top_level.txt
stylometry_utils-0.1.3.dist-info/RECORD
