Metadata-Version: 2.1
Name: stylometry-utils
Version: 0.1.3
Summary: Collection of functions and utilities to run stylometry experiments
Author: Simone Martin Marotta
Requires-Dist: keras
Requires-Dist: nltk
Requires-Dist: numpy
Requires-Dist: openpyxl
Requires-Dist: pandas
Requires-Dist: scikit-learn
Requires-Dist: scipy
Requires-Dist: tensorboard
Requires-Dist: tensorboard-data-server
Requires-Dist: tensorboard-plugin-wit
Requires-Dist: tensorflow
Requires-Dist: tensorflow-estimator
Requires-Dist: tensorflow-intel
Requires-Dist: tensorflow-io-gcs-filesystem
Requires-Dist: tokenizers
Requires-Dist: tornado
Requires-Dist: tqdm
Requires-Dist: transformers
Requires-Dist: typing-extensions
